CHANGES.txt
COPYRIGHT.txt
LICENSE.txt
README.txt
TODO.txt
ez_setup.py
setup.cfg
setup.py
docs/Makefile
docs/api.rst
docs/conf.py
docs/glossary.rst
docs/index.rst
docs/install.rst
docs/internals.rst
docs/usage.rst
docs/code/sample.py
docs/code/subscribers.py
repoze/__init__.py
repoze.session.egg-info/PKG-INFO
repoze.session.egg-info/SOURCES.txt
repoze.session.egg-info/dependency_links.txt
repoze.session.egg-info/entry_points.txt
repoze.session.egg-info/namespace_packages.txt
repoze.session.egg-info/not-zip-safe
repoze.session.egg-info/requires.txt
repoze.session.egg-info/top_level.txt
repoze/session/__init__.py
repoze/session/data.py
repoze/session/interfaces.py
repoze/session/linkedlist.py
repoze/session/manager.py
repoze/session/tests/__init__.py
repoze/session/tests/test_data.py
repoze/session/tests/test_linkedlist.py
repoze/session/tests/test_manager.py